pianum/__init__.py
pianum/struct.py
pianum-0.0.1.dist-info/METADATA
pianum-0.0.1.dist-info/WHEEL
pianum-0.0.1.dist-info/licenses/LICENSE
pianum-0.0.1.dist-info/RECORD
