Metadata-Version: 2.1
Name: pianum
Version: 0.0.1
Summary: Music theory tools
Project-URL: Homepage, https://github.com/chemtrails/pianum
Project-URL: Bug Tracker, https://github.com/chemtrails/pianum/issues
License-File: LICENSE
Classifier: License :: OSI Approved
Classifier: Operating System :: OS Independent
Classifier: Programming Language :: Python :: 3
Requires-Python: >=3.6
